spndarray/__init__.py
spndarray/spndarray.py
spndarray-0.0.1.dist-info/METADATA
spndarray-0.0.1.dist-info/RECORD
spndarray-0.0.1.dist-info/WHEEL
spndarray-0.0.1.dist-info/top_level.txt
