Metadata-Version: 2.1
Name: spndarray
Version: 0.0.1
Summary: Library for manipulating spatial arrays.
Home-page: UNKNOWN
Author: Jordan Matelsky
Author-email: jordan@matelsky.com
License: Apache 2.0
Download-URL: https://github.com/j6k4m8/spndarray/tarball/0.0.1
Keywords: volume,spatial,array
Platform: UNKNOWN
Classifier: Development Status :: 4 - Beta
Classifier: Intended Audience :: Developers
Classifier: Programming Language :: Python :: 3.4
Classifier: Programming Language :: Python :: 3.5
Requires-Dist: numpy
